.hgignore
.hgtags
ISSUES
LICENSE.txt
Makefile
README.rst
TODO
setup.cfg
setup.py
bin/uta-dump-bed
doc/Makefile
doc/command notes
doc/description.txt
doc/design
doc/ensembl-rest
doc/goals
doc/misc-figures.odg
doc/misc-figures.pdf
doc/source/conf.py
doc/source/database.rst
doc/source/db_loading.rst
doc/source/db_schema.rst
doc/source/description.rst
doc/source/examples.rst
doc/source/getting_started.rst
doc/source/index.rst
doc/source/installation.rst
doc/source/modules.rst
doc/source/modules_ud_transcriptdb.rst
doc/source/overview.rst
doc/static/favicon.ico
doc/static/uta-logo.png
doc/themes/invitae/instlogo.html
doc/themes/invitae/layout.html
doc/themes/invitae/theme.conf
doc/themes/invitae/static/dialog-note.png
doc/themes/invitae/static/dialog-seealso.png
doc/themes/invitae/static/dialog-todo.png
doc/themes/invitae/static/dialog-topic.png
doc/themes/invitae/static/dialog-warning.png
doc/themes/invitae/static/epub.css
doc/themes/invitae/static/footerbg.png
doc/themes/invitae/static/headerbg.png
doc/themes/invitae/static/ie6.css
doc/themes/invitae/static/invitae.css_t
doc/themes/invitae/static/invitae.png
doc/themes/invitae/static/middlebg.png
doc/themes/invitae/static/transparent.gif
etc/global.conf
etc/logging.conf
etc/pylintrc
etc/test.conf
etc/uta_dev@localhost.conf
etc/uta_dev@uic.com
loading/Makefile
loading/README
loading/aux/acmg57.hgnc
loading/aux/ck.tsv
loading/bic/bic.exonset.gz
loading/bic/bic.seqinfo.gz
loading/bic/bic.txinfo.gz
loading/bic/brca1.fasta
loading/bic/brca2.fasta
loading/lrg/lrg.exonset.gz
loading/lrg/lrg.fasta.tgz
loading/lrg/lrg.txinfo.gz
loading/main/genes.hgnc.gz
loading/test/ensembl.exonset.gz
loading/test/ensembl.seqinfo.gz
loading/test/ensembl.txinfo.gz
loading/test/genes
loading/test/ncbi-core.seqinfo.gz
loading/test/ncbi.exonset.gz
loading/test/ncbi.geneinfo.gz
loading/test/ncbi.seqinfo.gz
loading/test/ncbi.txinfo.gz
loading/test/sequences.fa.gz
loading/test/ucsc.exonset.gz
loading/test/uta0.exonset.gz
loading/test/uta0.txinfo.gz
uta.egg-info/PKG-INFO
uta.egg-info/SOURCES.txt
uta.egg-info/dependency_links.txt
uta.egg-info/requires.txt
uta.egg-info/top_level.txt
uta.egg-info/zip-safe
