Metadata-Version: 1.1
Name: uta
Version: 0.1.8
Summary: Universal Transcript Archive
Home-page: https://bitbucket.org/uta/uta
Author: UTA Contributors
Author-email: reecehart+uta@gmail.com
License: Apache License 2.0 (http://www.apache.org/licenses/LICENSE-2.0)
Keywords: bioinformatics,computational biology,genome variants,genome variation,genomic variants,genomic variation,genomics,hgvs
Platform: UNKNOWN
Classifier: Development Status :: 3 - Alpha
Classifier: Intended Audience :: Developers
Classifier: Intended Audience :: Healthcare Industry
Classifier: Intended Audience :: Science/Research
Classifier: License :: OSI Approved :: Apache Software License
Classifier: Operating System :: OS Independent
Classifier: Programming Language :: Python :: 2
Classifier: Programming Language :: Python
Classifier: Topic :: Database :: Front-Ends
Classifier: Topic :: Scientific/Engineering :: Bio-Informatics
Classifier: Topic :: Scientific/Engineering :: Medical Science Apps.
